compose_companion/__init__.py
compose_companion/cli.py
compose_companion/configurations.py
compose_companion/functions.py
compose_companion-0.2.2.dist-info/entry_points.txt
compose_companion-0.2.2.dist-info/WHEEL
compose_companion-0.2.2.dist-info/METADATA
compose_companion-0.2.2.dist-info/RECORD
