Metadata-Version: 2.1
Name: compose-companion
Version: 0.2.2
Summary: A companion for Docker Compose
Author: Natália Fonseca
Author-email: natalia@nataliafonseca.dev
Requires-Python: >=3.10,<4.0
Classifier: Programming Language :: Python :: 3
Classifier: Programming Language :: Python :: 3.10
Classifier: Programming Language :: Python :: 3.11
Requires-Dist: python-dotenv (>=0.21.0,<0.22.0)
Requires-Dist: pyyaml (>=6.0,<7.0)
Requires-Dist: rich (>=12.6.0,<13.0.0)
Requires-Dist: typer (>=0.7.0,<0.8.0)
Requires-Dist: yaml-env-var-parser (>=1.1.1,<2.0.0)
